python_dataset/__init__.py
python_dataset/extractor.py
python_dataset/property/__init__.py
python_dataset/property/main.py
python_dataset/sample/sample.wav
python_dataset/utils.py
python_dataset/wave/__init__.py
python_dataset/wave/main.py
python_dataset-0.0.4.dist-info/WHEEL
python_dataset-0.0.4.dist-info/METADATA
python_dataset-0.0.4.dist-info/RECORD
