Metadata-Version: 2.1
Name: python-dataset
Version: 0.0.4
Summary: 
Author: kjun1
Author-email: p.k.maejima1211@icloud.com
Requires-Python: >=3.7.11,<4.0.0
Classifier: Programming Language :: Python :: 3
Classifier: Programming Language :: Python :: 3.8
Classifier: Programming Language :: Python :: 3.9
Requires-Dist: jupyterlab (>=3.1.4,<4.0.0)
Requires-Dist: librosa (>=0.8.1,<0.9.0)
Requires-Dist: opencv-python (>=4.5.2,<5.0.0)
Requires-Dist: pandas (>=1.2.4,<2.0.0)
Requires-Dist: pysptk (>=0.1.18,<0.2.0)
Requires-Dist: pyworld (>=0.2.12,<0.3.0)
Requires-Dist: soxr (>=0.2.6,<0.3.0)
Requires-Dist: toml (>=0.10.2,<0.11.0)
Requires-Dist: torch (>=1.10.0,<2.0.0)
Requires-Dist: torchaudio (>=0.10.0,<0.11.0)
